beanis/__init__.py
beanis/exceptions.py
beanis/py.typed
beanis/pydantic_check.py
beanis/test.py
beanis/odm/__init__.py
beanis/odm/actions.py
beanis/odm/custom_encoders.py
beanis/odm/documents.py
beanis/odm/fields.py
beanis/odm/indexes.py
beanis/odm/registry.py
beanis/odm/custom_types/__init__.py
beanis/odm/custom_types/decimal.py
beanis/odm/interfaces/__init__.py
beanis/odm/interfaces/clone.py
beanis/odm/interfaces/detector.py
beanis/odm/interfaces/getters.py
beanis/odm/interfaces/inheritance.py
beanis/odm/interfaces/setters.py
beanis/odm/settings/__init__.py
beanis/odm/settings/base.py
beanis/odm/settings/document.py
beanis/odm/utils/__init__.py
beanis/odm/utils/dump.py
beanis/odm/utils/encoder.py
beanis/odm/utils/general.py
beanis/odm/utils/init.py
beanis/odm/utils/parsing.py
beanis/odm/utils/projection.py
beanis/odm/utils/pydantic.py
beanis/odm/utils/self_validation.py
beanis/odm/utils/state.py
beanis/odm/utils/typing.py
beanis-0.2.0.dist-info/licenses/LICENSE
beanis-0.2.0.dist-info/WHEEL
beanis-0.2.0.dist-info/METADATA
beanis-0.2.0.dist-info/RECORD
