Metadata-Version: 2.4
Name: beanis
Version: 0.2.0
Summary: Asynchronous Python ODM for Redis
Keywords: redis,odm,orm,pydantic,async,python
Author-email: Andrei Stefan Bejgu <stefan.bejgu@gmail.com>
Requires-Python: >=3.9,<4.0
Classifier: License :: OSI Approved :: Apache Software License
Classifier: Development Status :: 5 - Production/Stable
Classifier: Intended Audience :: Developers
Classifier: Operating System :: OS Independent
Classifier: Topic :: Database
Classifier: Topic :: Software Development :: Libraries :: Python Modules
Classifier: Typing :: Typed
License-File: LICENSE
Requires-Dist: redis[hiredis]>=5.0.0
Requires-Dist: pydantic>=1.10,<3.0
Requires-Dist: lazy-model==0.2.0
Requires-Dist: msgspec>=0.18.0
Requires-Dist: typing-extensions>=4.7; python_version < '3.11'
Requires-Dist: Pygments>=2.8.0 ; extra == "doc"
Requires-Dist: Markdown>=3.3 ; extra == "doc"
Requires-Dist: pydoc-markdown>=4.8 ; extra == "doc"
Requires-Dist: mkdocs>=1.4 ; extra == "doc"
Requires-Dist: mkdocs-material>=9.0 ; extra == "doc"
Requires-Dist: jinja2>=3.0.3 ; extra == "doc"
Requires-Dist: pytest>=6.0.0 ; extra == "test"
Requires-Dist: pytest-asyncio>=0.21.0 ; extra == "test"
Requires-Dist: pytest-cov>=2.8.1 ; extra == "test"
Requires-Dist: fakeredis[lua]>=2.20.0 ; extra == "test"
Requires-Dist: flake8>=3 ; extra == "test"
Requires-Dist: pyright>=0 ; extra == "test"
Requires-Dist: httpx>=0.23.0 ; extra == "test"
Requires-Dist: fastapi>=0.100 ; extra == "test"
Requires-Dist: pydantic-settings>=2 ; extra == "test"
Requires-Dist: pydantic-extra-types>=2 ; extra == "test"
Requires-Dist: pydantic[email] ; extra == "test"
Project-URL: homepage, https://github.com/andreim14/beanis
Project-URL: repository, https://github.com/andreim14/beanis
Provides-Extra: doc
Provides-Extra: test
